sentivi/__init__.py
sentivi/base_model.py
sentivi/ensemble.py
sentivi/pipeline.py
sentivi/service.py
sentivi/text_processor.py
sentivi/classifier/__init__.py
sentivi/classifier/decision_tree.py
sentivi/classifier/gaussian_process.py
sentivi/classifier/lstm.py
sentivi/classifier/mlp.py
sentivi/classifier/naive_bayes.py
sentivi/classifier/nearest_centroid.py
sentivi/classifier/nn_clf.py
sentivi/classifier/sgd.py
sentivi/classifier/sklearn_clf.py
sentivi/classifier/svm.py
sentivi/classifier/text_cnn.py
sentivi/classifier/transformer.py
sentivi/data/__init__.py
sentivi/data/data_loader.py
sentivi/data/text_encoder.py
sentivi-1.1.0.dist-info/LICENSE
sentivi-1.1.0.dist-info/METADATA
sentivi-1.1.0.dist-info/WHEEL
sentivi-1.1.0.dist-info/top_level.txt
sentivi-1.1.0.dist-info/RECORD
