Metadata-Version: 2.1
Name: sentivi
Version: 1.1.0
Summary: A simple tool for Vietnamese Sentiment Analysis
Home-page: https://github.com/vndee/sentivi
Author: Duy V. Huynh
Author-email: hvd.huynhduy@gmail.com
License: MIT
Platform: UNKNOWN
Classifier: License :: OSI Approved :: MIT License
Classifier: Programming Language :: Python :: 3
Classifier: Programming Language :: Python :: 3.7
Requires-Dist: alabaster (==0.7.12)
Requires-Dist: Babel (==2.8.0)
Requires-Dist: bleach (==3.2.1)
Requires-Dist: blis (==0.4.1)
Requires-Dist: bump2version (==1.0.0)
Requires-Dist: bumpversion (==0.6.0)
Requires-Dist: catalogue (==1.0.0)
Requires-Dist: certifi (==2020.6.20)
Requires-Dist: cffi (==1.14.3)
Requires-Dist: chardet (==3.0.4)
Requires-Dist: click (==7.1.2)
Requires-Dist: colorama (==0.4.3)
Requires-Dist: cryptography (==3.1.1)
Requires-Dist: cymem (==2.0.3)
Requires-Dist: dill (==0.3.2)
Requires-Dist: docutils (==0.16)
Requires-Dist: fastapi (==0.61.1)
Requires-Dist: filelock (==3.0.12)
Requires-Dist: future (==0.18.2)
Requires-Dist: gensim (==3.8.3)
Requires-Dist: h11 (==0.10.0)
Requires-Dist: idna (==2.10)
Requires-Dist: imagesize (==1.2.0)
Requires-Dist: jeepney (==0.4.3)
Requires-Dist: Jinja2 (==2.11.2)
Requires-Dist: joblib (==0.16.0)
Requires-Dist: keyring (==21.4.0)
Requires-Dist: MarkupSafe (==1.1.1)
Requires-Dist: msmb-theme (==1.2.0)
Requires-Dist: murmurhash (==1.0.2)
Requires-Dist: numpy (==1.19.2)
Requires-Dist: packaging (==20.4)
Requires-Dist: pkginfo (==1.5.0.1)
Requires-Dist: plac (==1.1.3)
Requires-Dist: preshed (==3.0.2)
Requires-Dist: pycparser (==2.20)
Requires-Dist: pydantic (==1.6.1)
Requires-Dist: Pygments (==2.7.1)
Requires-Dist: pyparsing (==2.4.7)
Requires-Dist: python-crfsuite (==0.9.7)
Requires-Dist: python-multipart (==0.0.5)
Requires-Dist: pytz (==2020.1)
Requires-Dist: pyvi (==0.1)
Requires-Dist: readme-renderer (==26.0)
Requires-Dist: regex (==2020.9.27)
Requires-Dist: requests (==2.24.0)
Requires-Dist: requests-toolbelt (==0.9.1)
Requires-Dist: rfc3986 (==1.4.0)
Requires-Dist: sacremoses (==0.0.43)
Requires-Dist: scikit-learn (==0.23.2)
Requires-Dist: scipy (==1.5.2)
Requires-Dist: SecretStorage (==3.1.2)
Requires-Dist: sentencepiece (==0.1.91)
Requires-Dist: six (==1.15.0)
Requires-Dist: sklearn-crfsuite (==0.3.6)
Requires-Dist: smart-open (==2.2.0)
Requires-Dist: snowballstemmer (==2.0.0)
Requires-Dist: spacy (==2.3.2)
Requires-Dist: Sphinx (==3.2.1)
Requires-Dist: sphinx-drove-theme (==1.11.0)
Requires-Dist: sphinx-rtd-theme (==0.5.0)
Requires-Dist: sphinxcontrib-applehelp (==1.0.2)
Requires-Dist: sphinxcontrib-devhelp (==1.0.2)
Requires-Dist: sphinxcontrib-htmlhelp (==1.0.3)
Requires-Dist: sphinxcontrib-jsmath (==1.0.1)
Requires-Dist: sphinxcontrib-qthelp (==1.0.3)
Requires-Dist: sphinxcontrib-serializinghtml (==1.1.4)
Requires-Dist: srsly (==1.0.2)
Requires-Dist: starlette (==0.13.6)
Requires-Dist: tabulate (==0.8.7)
Requires-Dist: thinc (==7.4.1)
Requires-Dist: threadpoolctl (==2.1.0)
Requires-Dist: tokenizers (==0.8.1rc2)
Requires-Dist: tqdm (==4.49.0)
Requires-Dist: transformers (==3.1.0)
Requires-Dist: twine (==3.2.0)
Requires-Dist: urllib3 (==1.25.10)
Requires-Dist: uvicorn (==0.12.0)
Requires-Dist: wasabi (==0.8.0)
Requires-Dist: webencodings (==0.5.1)
